{
    "@context": "http://www.w3.org/ns/csvw",
    "@id": "http://gss-data.org.uk/def/climate-change/concept-scheme/sic-section",
    "url": "sic-section.csv",
    "tableSchema": {
        "columns": [
            {
                "titles": "Label",
                "name": "label",
                "datatype": "string",
                "required": true,
                "propertyUrl": "rdfs:label"
            },
            {
                "titles": "Notation",
                "name": "notation",
                "datatype": {
                    "base": "string",
                    "format": "^-?[\\w\\.\\/\\+]+(-[\\w\\.\\/\\+]+)*$"
                },
                "required": true,
                "propertyUrl": "skos:notation"
            },
            {
                "titles": "Parent Notation",
                "name": "parent_notation",
                "datatype": {
                    "base": "string",
                    "format": "^(-?[\\w\\.\\/\\+]+(-[\\w\\.\\/\\+]+)*|)$"
                },
                "required": false,
                "propertyUrl": "skos:broader",
                "valueUrl": "http://gss-data.org.uk/def/climate-change/concept/sic-section/{+parent_notation}"
            },
            {
                "titles": "Sort Priority",
                "name": "sort",
                "datatype": "integer",
                "required": false,
                "propertyUrl": "http://www.w3.org/ns/ui#sortPriority"
            },
            {
                "titles": "Description",
                "name": "description",
                "datatype": "string",
                "required": false,
                "propertyUrl": "rdfs:comment"
            },
            {
                "virtual": true,
                "propertyUrl": "rdf:type",
                "valueUrl": "skos:Concept"
            },
            {
                "virtual": true,
                "propertyUrl": "skos:inScheme",
                "valueUrl": "http://gss-data.org.uk/def/climate-change/concept-scheme/sic-section"
            }
        ],
        "primaryKey": "notation",
        "aboutUrl": "http://gss-data.org.uk/def/climate-change/concept/sic-section/{+notation}"
    },
    "rdfs:label": "SIC Section",
    "dc:title": "SIC Section",
    "prov:hadDerivation": {
        "@id": "http://gss-data.org.uk/def/climate-change/concept-scheme/sic-section",
        "@type": [
            "skos:ConceptScheme",
            "http://publishmydata.com/pmdcat#ConceptScheme"
        ]
    },
    "rdfs:seeAlso": [
        {
            "@id": "http://gss-data.org.uk/def/climate-change/concept-scheme/sic-section/dataset",
            "@type": [
                "dcat:Dataset",
                "http://publishmydata.com/pmdcat#Dataset"
            ],
            "rdfs:label": "SIC Section",
            "dc:title": "SIC Section",
            "http://publishmydata.com/pmdcat#datasetContents": {
                "@id": "http://gss-data.org.uk/def/climate-change/concept-scheme/sic-section"
            },
            "rdfs:comment": "Dataset representing the 'SIC Section' code list.",
            "http://publishmydata.com/pmdcat#graph": {
                "@id": "http://gss-data.org.uk/def/climate-change/concept-scheme/sic-section"
            },
            "dc:modified": {
                "@type": "dateTime",
                "@value": "2021-05-20T11:35:12.591977"
            },
            "dc:issued": {
                "@type": "dateTime",
                "@value": "2021-02-03T11:35:22.815540"
            }
        },
        {
            "@id": "http://gss-data.org.uk/catalog/vocabularies",
            "dcat:record": {
                "@id": "http://gss-data.org.uk/def/climate-change/concept-scheme/sic-section/catalog-record"
            }
        },
        {
            "@id": "http://gss-data.org.uk/def/climate-change/concept-scheme/sic-section/catalog-record",
            "@type": "dcat:CatalogRecord",
            "dc:title": "SIC Section Catalog Record",
            "rdfs:label": "SIC Section Catalog Record",
            "dc:issued": {
                "@type": "dateTime",
                "@value": "2021-10-08T11:59:10.942836"
            },
            "foaf:primaryTopic": {
                "@id": "http://gss-data.org.uk/def/climate-change/concept-scheme/sic-section/dataset"
            },
            "dc:modified": {
                "@type": "dateTime",
                "@value": "2021-10-08T11:59:10.942836"
            },
            "http://publishmydata.com/pmdcat#metadataGraph": {
                "@id": "http://gss-data.org.uk/def/climate-change/concept-scheme/sic-section"
            }
        }
    ]
}